LICENSE.txt
README.md
setup.cfg
setup.py
mnn/__init__.py
mnn/activations.py
mnn/constants.py
mnn/csvdata.py
mnn/csvreader.py
mnn/dataset.py
mnn/layer.py
mnn/load.py
mnn/loader.py
mnn/network.py
mnn/neuron.py
mnn/save.py
mnn/trainer.py
mnn/utils.py
mnn/weight.py
mnnlib.egg-info/PKG-INFO
mnnlib.egg-info/SOURCES.txt
mnnlib.egg-info/dependency_links.txt
mnnlib.egg-info/top_level.txt