Metadata-Version: 2.1
Name: mnnlib
Version: 0.3.10
Summary: Minejerik neural network library
Home-page: https://github.com/Minejerik/mnnlibv2
Author: Minejerik
Author-email: jaanerikf@gmail.com
Keywords: Minejerik,Ai,Neural Network
Classifier: Development Status :: 3 - Alpha
Classifier: Intended Audience :: Developers
Classifier: Topic :: Software Development :: Build Tools
Classifier: License :: OSI Approved :: MIT License
Classifier: Programming Language :: Python :: 3
Classifier: Programming Language :: Python :: 3.7
Classifier: Programming Language :: Python :: 3.8
Classifier: Programming Language :: Python :: 3.9
Classifier: Programming Language :: Python :: 3.10
Classifier: Programming Language :: Python :: 3 :: Only
Requires-Python: >=3.3, <4
License-File: LICENSE.txt
